[
    {
        "id": 1,
        "title": "Task 1",
        "description": "This is the description for task 1.",
        "completedAt": "2024-08-09T14:09:32Z",
        "createdAt": "2024-08-05T14:09:32Z",
        "updatedAt": "2024-08-10T14:09:32Z"
    },
    {
        "id": 2,
        "title": "Task 2",
        "description": "This is the description for task 2.",
        "completedAt": null,
        "createdAt": "2024-10-01T14:09:32Z",
        "updatedAt": null
    },
    {
        "id": 3,
        "title": "Task 3",
        "description": "This is the description for task 3.",
        "completedAt": null,
        "createdAt": "2024-11-02T14:09:32Z",
        "updatedAt": null
    },
    {
        "id": 4,
        "title": "Task 4",
        "description": "This is the description for task 4.",
        "completedAt": null,
        "createdAt": "2024-08-03T14:09:32Z",
        "updatedAt": null
    },
    {
        "id": 5,
        "title": "Task 5",
        "description": "This is the description for task 5.",
        "completedAt": null,
        "createdAt": "2024-11-02T14:09:32Z",
        "updatedAt": null
    },
    {
        "id": 6,
        "title": "Task 6",
        "description": "This is the description for task 6.",
        "completedAt": "2024-09-18T14:09:32Z",
        "createdAt": "2024-09-14T14:09:32Z",
        "updatedAt": "2024-09-25T14:09:32Z"
    },
    {
        "id": 7,
        "title": "Task 7",
        "description": "This is the description for task 7.",
        "completedAt": "2024-09-30T14:09:32Z",
        "createdAt": "2024-08-31T14:09:32Z",
        "updatedAt": "2024-10-08T14:09:32Z"
    },
    {
        "id": 8,
        "title": "Task 8",
        "description": "This is the description for task 8.",
        "completedAt": "2024-08-24T14:09:32Z",
        "createdAt": "2024-08-08T14:09:32Z",
        "updatedAt": "2024-08-30T14:09:32Z"
    },
    {
        "id": 9,
        "title": "Task 9",
        "description": "This is the description for task 9.",
        "completedAt": "2024-11-06T14:09:32Z",
        "createdAt": "2024-10-18T14:09:32Z",
        "updatedAt": "2024-11-16T14:09:32Z"
    },
    {
        "id": 10,
        "title": "Task 10",
        "description": "This is the description for task 10.",
        "completedAt": "2024-10-03T14:09:32Z",
        "createdAt": "2024-09-15T14:09:32Z",
        "updatedAt": "2024-10-11T14:09:32Z"
    },
    {
        "id": 11,
        "title": "Task 11",
        "description": "This is the description for task 11.",
        "completedAt": "2024-10-21T14:09:32Z",
        "createdAt": "2024-10-03T14:09:32Z",
        "updatedAt": "2024-10-31T14:09:32Z"
    },
    {
        "id": 12,
        "title": "Task 12",
        "description": "This is the description for task 12.",
        "completedAt": null,
        "createdAt": "2024-09-10T14:09:32Z",
        "updatedAt": null
    },
    {
        "id": 13,
        "title": "Task 13",
        "description": "This is the description for task 13.",
        "completedAt": null,
        "createdAt": "2024-08-22T14:09:32Z",
        "updatedAt": null
    },
    {
        "id": 14,
        "title": "Task 14",
        "description": "This is the description for task 14.",
        "completedAt": "2024-11-07T14:09:32Z",
        "createdAt": "2024-11-01T14:09:32Z",
        "updatedAt": "2024-11-15T14:09:32Z"
    },
    {
        "id": 15,
        "title": "Task 15",
        "description": "This is the description for task 15.",
        "completedAt": "2024-10-10T14:09:32Z",
        "createdAt": "2024-09-11T14:09:32Z",
        "updatedAt": "2024-10-17T14:09:32Z"
    },
    {
        "id": 16,
        "title": "Task 16",
        "description": "This is the description for task 16.",
        "completedAt": "2024-08-15T14:09:32Z",
        "createdAt": "2024-08-04T14:09:32Z",
        "updatedAt": "2024-08-23T14:09:32Z"
    },
    {
        "id": 17,
        "title": "Task 17",
        "description": "This is the description for task 17.",
        "completedAt": null,
        "createdAt": "2024-09-23T14:09:32Z",
        "updatedAt": null
    },
    {
        "id": 18,
        "title": "Task 18",
        "description": "This is the description for task 18.",
        "completedAt": null,
        "createdAt": "2024-10-03T14:09:32Z",
        "updatedAt": null
    },
    {
        "id": 19,
        "title": "Task 19",
        "description": "This is the description for task 19.",
        "completedAt": "2024-11-24T14:09:32Z",
        "createdAt": "2024-11-08T14:09:32Z",
        "updatedAt": "2024-11-28T14:09:32Z"
    },
    {
        "id": 20,
        "title": "Task 20",
        "description": "This is the description for task 20.",
        "completedAt": null,
        "createdAt": "2024-08-24T14:09:32Z",
        "updatedAt": null
    },
    {
        "id": 21,
        "title": "Task 21",
        "description": "This is the description for task 21.",
        "completedAt": null,
        "createdAt": "2024-09-15T14:09:32Z",
        "updatedAt": null
    },
    {
        "id": 22,
        "title": "Task 22",
        "description": "This is the description for task 22.",
        "completedAt": "2024-10-14T14:09:32Z",
        "createdAt": "2024-10-05T14:09:32Z",
        "updatedAt": "2024-10-24T14:09:32Z"
    },
    {
        "id": 23,
        "title": "Task 23",
        "description": "This is the description for task 23.",
        "completedAt": null,
        "createdAt": "2024-09-02T14:09:32Z",
        "updatedAt": null
    },
    {
        "id": 24,
        "title": "Task 24",
        "description": "This is the description for task 24.",
        "completedAt": null,
        "createdAt": "2024-10-31T14:09:32Z",
        "updatedAt": null
    },
    {
        "id": 25,
        "title": "Task 25",
        "description": "This is the description for task 25.",
        "completedAt": "2024-11-08T14:09:32Z",
        "createdAt": "2024-10-10T14:09:32Z",
        "updatedAt": "2024-11-16T14:09:32Z"
    },
    {
        "id": 26,
        "title": "Task 26",
        "description": "This is the description for task 26.",
        "completedAt": null,
        "createdAt": "2024-08-07T14:09:32Z",
        "updatedAt": null
    },
    {
        "id": 27,
        "title": "Task 27",
        "description": "This is the description for task 27.",
        "completedAt": null,
        "createdAt": "2024-10-10T14:09:32Z",
        "updatedAt": null
    },
    {
        "id": 28,
        "title": "Task 28",
        "description": "This is the description for task 28.",
        "completedAt": "2024-09-04T14:09:32Z",
        "createdAt": "2024-08-31T14:09:32Z",
        "updatedAt": "2024-09-10T14:09:32Z"
    },
    {
        "id": 29,
        "title": "Task 29",
        "description": "This is the description for task 29.",
        "completedAt": "2024-08-16T14:09:32Z",
        "createdAt": "2024-08-13T14:09:32Z",
        "updatedAt": "2024-08-24T14:09:32Z"
    },
    {
        "id": 30,
        "title": "Task 30",
        "description": "This is the description for task 30.",
        "completedAt": null,
        "createdAt": "2024-11-01T14:09:32Z",
        "updatedAt": null
    },
    {
        "id": 31,
        "title": "Task 31",
        "description": "This is the description for task 31.",
        "completedAt": null,
        "createdAt": "2024-11-03T14:09:32Z",
        "updatedAt": null
    },
    {
        "id": 32,
        "title": "Task 32",
        "description": "This is the description for task 32.",
        "completedAt": "2024-11-06T14:09:32Z",
        "createdAt": "2024-10-09T14:09:32Z",
        "updatedAt": "2024-11-16T14:09:32Z"
    },
    {
        "id": 33,
        "title": "Task 33",
        "description": "This is the description for task 33.",
        "completedAt": null,
        "createdAt": "2024-11-04T14:09:32Z",
        "updatedAt": null
    },
    {
        "id": 34,
        "title": "Task 34",
        "description": "This is the description for task 34.",
        "completedAt": null,
        "createdAt": "2024-10-07T14:09:32Z",
        "updatedAt": null
    },
    {
        "id": 35,
        "title": "Task 35",
        "description": "This is the description for task 35.",
        "completedAt": null,
        "createdAt": "2024-10-28T14:09:32Z",
        "updatedAt": null
    },
    {
        "id": 36,
        "title": "Task 36",
        "description": "This is the description for task 36.",
        "completedAt": "2024-08-12T14:09:32Z",
        "createdAt": "2024-08-05T14:09:32Z",
        "updatedAt": "2024-08-19T14:09:32Z"
    },
    {
        "id": 37,
        "title": "Task 37",
        "description": "This is the description for task 37.",
        "completedAt": "2024-11-21T14:09:32Z",
        "createdAt": "2024-11-04T14:09:32Z",
        "updatedAt": "2024-11-28T14:09:32Z"
    },
    {
        "id": 38,
        "title": "Task 38",
        "description": "This is the description for task 38.",
        "completedAt": null,
        "createdAt": "2024-08-04T14:09:32Z",
        "updatedAt": null
    },
    {
        "id": 39,
        "title": "Task 39",
        "description": "This is the description for task 39.",
        "completedAt": "2024-09-17T14:09:32Z",
        "createdAt": "2024-09-14T14:09:32Z",
        "updatedAt": "2024-09-18T14:09:32Z"
    },
    {
        "id": 40,
        "title": "Task 40",
        "description": "This is the description for task 40.",
        "completedAt": null,
        "createdAt": "2024-09-27T14:09:32Z",
        "updatedAt": null
    },
    {
        "id": 41,
        "title": "Task 41",
        "description": "This is the description for task 41.",
        "completedAt": "2024-11-15T14:09:32Z",
        "createdAt": "2024-10-29T14:09:32Z",
        "updatedAt": "2024-11-25T14:09:32Z"
    },
    {
        "id": 42,
        "title": "Task 42",
        "description": "This is the description for task 42.",
        "completedAt": "2024-09-12T14:09:32Z",
        "createdAt": "2024-09-01T14:09:32Z",
        "updatedAt": "2024-09-13T14:09:32Z"
    },
    {
        "id": 43,
        "title": "Task 43",
        "description": "This is the description for task 43.",
        "completedAt": null,
        "createdAt": "2024-08-31T14:09:32Z",
        "updatedAt": null
    },
    {
        "id": 44,
        "title": "Task 44",
        "description": "This is the description for task 44.",
        "completedAt": null,
        "createdAt": "2024-11-01T14:09:32Z",
        "updatedAt": null
    },
    {
        "id": 45,
        "title": "Task 45",
        "description": "This is the description for task 45.",
        "completedAt": null,
        "createdAt": "2024-09-01T14:09:32Z",
        "updatedAt": null
    },
    {
        "id": 46,
        "title": "Task 46",
        "description": "This is the description for task 46.",
        "completedAt": "2024-11-02T14:09:32Z",
        "createdAt": "2024-10-16T14:09:32Z",
        "updatedAt": "2024-11-12T14:09:32Z"
    },
    {
        "id": 47,
        "title": "Task 47",
        "description": "This is the description for task 47.",
        "completedAt": "2024-10-20T14:09:32Z",
        "createdAt": "2024-09-24T14:09:32Z",
        "updatedAt": "2024-10-26T14:09:32Z"
    },
    {
        "id": 48,
        "title": "Task 48",
        "description": "This is the description for task 48.",
        "completedAt": null,
        "createdAt": "2024-08-26T14:09:32Z",
        "updatedAt": null
    },
    {
        "id": 49,
        "title": "Task 49",
        "description": "This is the description for task 49.",
        "completedAt": "2024-10-10T14:09:32Z",
        "createdAt": "2024-09-12T14:09:32Z",
        "updatedAt": "2024-10-12T14:09:32Z"
    },
    {
        "id": 50,
        "title": "Task 50",
        "description": "This is the description for task 50.",
        "completedAt": null,
        "createdAt": "2024-08-19T14:09:32Z",
        "updatedAt": null
    },
    {
        "id": 51,
        "title": "Task 51",
        "description": "This is the description for task 51.",
        "completedAt": null,
        "createdAt": "2024-08-08T14:09:32Z",
        "updatedAt": null
    },
    {
        "id": 52,
        "title": "Task 52",
        "description": "This is the description for task 52.",
        "completedAt": null,
        "createdAt": "2024-10-14T14:09:32Z",
        "updatedAt": null
    },
    {
        "id": 53,
        "title": "Task 53",
        "description": "This is the description for task 53.",
        "completedAt": null,
        "createdAt": "2024-09-02T14:09:32Z",
        "updatedAt": null
    },
    {
        "id": 54,
        "title": "Task 54",
        "description": "This is the description for task 54.",
        "completedAt": "2024-11-15T14:09:32Z",
        "createdAt": "2024-10-16T14:09:32Z",
        "updatedAt": "2024-11-17T14:09:32Z"
    },
    {
        "id": 55,
        "title": "Task 55",
        "description": "This is the description for task 55.",
        "completedAt": "2024-09-17T14:09:32Z",
        "createdAt": "2024-09-03T14:09:32Z",
        "updatedAt": "2024-09-23T14:09:32Z"
    },
    {
        "id": 56,
        "title": "Task 56",
        "description": "This is the description for task 56.",
        "completedAt": "2024-09-16T14:09:32Z",
        "createdAt": "2024-09-06T14:09:32Z",
        "updatedAt": "2024-09-18T14:09:32Z"
    },
    {
        "id": 57,
        "title": "Task 57",
        "description": "This is the description for task 57.",
        "completedAt": "2024-09-06T14:09:32Z",
        "createdAt": "2024-08-15T14:09:32Z",
        "updatedAt": "2024-09-14T14:09:32Z"
    },
    {
        "id": 58,
        "title": "Task 58",
        "description": "This is the description for task 58.",
        "completedAt": "2024-10-24T14:09:32Z",
        "createdAt": "2024-09-24T14:09:32Z",
        "updatedAt": "2024-11-01T14:09:32Z"
    },
    {
        "id": 59,
        "title": "Task 59",
        "description": "This is the description for task 59.",
        "completedAt": null,
        "createdAt": "2024-09-22T14:09:32Z",
        "updatedAt": null
    },
    {
        "id": 60,
        "title": "Task 60",
        "description": "This is the description for task 60.",
        "completedAt": null,
        "createdAt": "2024-10-19T14:09:32Z",
        "updatedAt": null
    },
    {
        "id": 61,
        "title": "Task 61",
        "description": "This is the description for task 61.",
        "completedAt": null,
        "createdAt": "2024-09-09T14:09:32Z",
        "updatedAt": null
    },
    {
        "id": 62,
        "title": "Task 62",
        "description": "This is the description for task 62.",
        "completedAt": "2024-09-04T14:09:32Z",
        "createdAt": "2024-08-31T14:09:32Z",
        "updatedAt": "2024-09-13T14:09:32Z"
    },
    {
        "id": 63,
        "title": "Task 63",
        "description": "This is the description for task 63.",
        "completedAt": "2024-10-02T14:09:32Z",
        "createdAt": "2024-09-26T14:09:32Z",
        "updatedAt": "2024-10-03T14:09:32Z"
    },
    {
        "id": 64,
        "title": "Task 64",
        "description": "This is the description for task 64.",
        "completedAt": "2024-09-15T14:09:32Z",
        "createdAt": "2024-08-23T14:09:32Z",
        "updatedAt": "2024-09-25T14:09:32Z"
    },
    {
        "id": 65,
        "title": "Task 65",
        "description": "This is the description for task 65.",
        "completedAt": "2024-11-17T14:09:32Z",
        "createdAt": "2024-11-01T14:09:32Z",
        "updatedAt": "2024-11-24T14:09:32Z"
    },
    {
        "id": 66,
        "title": "Task 66",
        "description": "This is the description for task 66.",
        "completedAt": null,
        "createdAt": "2024-09-21T14:09:32Z",
        "updatedAt": null
    },
    {
        "id": 67,
        "title": "Task 67",
        "description": "This is the description for task 67.",
        "completedAt": "2024-11-10T14:09:32Z",
        "createdAt": "2024-10-16T14:09:32Z",
        "updatedAt": "2024-11-16T14:09:32Z"
    },
    {
        "id": 68,
        "title": "Task 68",
        "description": "This is the description for task 68.",
        "completedAt": null,
        "createdAt": "2024-09-25T14:09:32Z",
        "updatedAt": null
    },
    {
        "id": 69,
        "title": "Task 69",
        "description": "This is the description for task 69.",
        "completedAt": "2024-10-05T14:09:32Z",
        "createdAt": "2024-10-01T14:09:32Z",
        "updatedAt": "2024-10-08T14:09:32Z"
    },
    {
        "id": 70,
        "title": "Task 70",
        "description": "This is the description for task 70.",
        "completedAt": "2024-09-15T14:09:32Z",
        "createdAt": "2024-08-21T14:09:32Z",
        "updatedAt": "2024-09-16T14:09:32Z"
    },
    {
        "id": 71,
        "title": "Task 71",
        "description": "This is the description for task 71.",
        "completedAt": null,
        "createdAt": "2024-09-12T14:09:32Z",
        "updatedAt": null
    },
    {
        "id": 72,
        "title": "Task 72",
        "description": "This is the description for task 72.",
        "completedAt": null,
        "createdAt": "2024-10-18T14:09:32Z",
        "updatedAt": null
    },
    {
        "id": 73,
        "title": "Task 73",
        "description": "This is the description for task 73.",
        "completedAt": null,
        "createdAt": "2024-10-08T14:09:32Z",
        "updatedAt": null
    },
    {
        "id": 74,
        "title": "Task 74",
        "description": "This is the description for task 74.",
        "completedAt": "2024-08-05T14:09:32Z",
        "createdAt": "2024-08-02T14:09:32Z",
        "updatedAt": "2024-08-14T14:09:32Z"
    },
    {
        "id": 75,
        "title": "Task 75",
        "description": "This is the description for task 75.",
        "completedAt": null,
        "createdAt": "2024-09-19T14:09:32Z",
        "updatedAt": null
    },
    {
        "id": 76,
        "title": "Task 76",
        "description": "This is the description for task 76.",
        "completedAt": "2024-10-05T14:09:32Z",
        "createdAt": "2024-09-27T14:09:32Z",
        "updatedAt": "2024-10-10T14:09:32Z"
    },
    {
        "id": 77,
        "title": "Task 77",
        "description": "This is the description for task 77.",
        "completedAt": "2024-09-07T14:09:32Z",
        "createdAt": "2024-08-21T14:09:32Z",
        "updatedAt": "2024-09-16T14:09:32Z"
    },
    {
        "id": 78,
        "title": "Task 78",
        "description": "This is the description for task 78.",
        "completedAt": null,
        "createdAt": "2024-08-05T14:09:32Z",
        "updatedAt": null
    },
    {
        "id": 79,
        "title": "Task 79",
        "description": "This is the description for task 79.",
        "completedAt": null,
        "createdAt": "2024-08-23T14:09:32Z",
        "updatedAt": null
    },
    {
        "id": 80,
        "title": "Task 80",
        "description": "This is the description for task 80.",
        "completedAt": "2024-10-17T14:09:32Z",
        "createdAt": "2024-10-06T14:09:32Z",
        "updatedAt": "2024-10-26T14:09:32Z"
    },
    {
        "id": 81,
        "title": "Task 81",
        "description": "This is the description for task 81.",
        "completedAt": "2024-09-23T14:09:32Z",
        "createdAt": "2024-09-03T14:09:32Z",
        "updatedAt": "2024-09-26T14:09:32Z"
    },
    {
        "id": 82,
        "title": "Task 82",
        "description": "This is the description for task 82.",
        "completedAt": "2024-08-18T14:09:32Z",
        "createdAt": "2024-08-01T14:09:32Z",
        "updatedAt": "2024-08-25T14:09:32Z"
    },
    {
        "id": 83,
        "title": "Task 83",
        "description": "This is the description for task 83.",
        "completedAt": "2024-09-18T14:09:32Z",
        "createdAt": "2024-08-25T14:09:32Z",
        "updatedAt": "2024-09-27T14:09:32Z"
    },
    {
        "id": 84,
        "title": "Task 84",
        "description": "This is the description for task 84.",
        "completedAt": null,
        "createdAt": "2024-10-06T14:09:32Z",
        "updatedAt": null
    },
    {
        "id": 85,
        "title": "Task 85",
        "description": "This is the description for task 85.",
        "completedAt": "2024-10-20T14:09:32Z",
        "createdAt": "2024-10-04T14:09:32Z",
        "updatedAt": "2024-10-26T14:09:32Z"
    },
    {
        "id": 86,
        "title": "Task 86",
        "description": "This is the description for task 86.",
        "completedAt": null,
        "createdAt": "2024-09-13T14:09:32Z",
        "updatedAt": null
    },
    {
        "id": 87,
        "title": "Task 87",
        "description": "This is the description for task 87.",
        "completedAt": "2024-09-22T14:09:32Z",
        "createdAt": "2024-08-31T14:09:32Z",
        "updatedAt": "2024-10-01T14:09:32Z"
    },
    {
        "id": 88,
        "title": "Task 88",
        "description": "This is the description for task 88.",
        "completedAt": "2024-09-23T14:09:32Z",
        "createdAt": "2024-09-02T14:09:32Z",
        "updatedAt": "2024-10-01T14:09:32Z"
    },
    {
        "id": 89,
        "title": "Task 89",
        "description": "This is the description for task 89.",
        "completedAt": null,
        "createdAt": "2024-09-07T14:09:32Z",
        "updatedAt": null
    },
    {
        "id": 90,
        "title": "Task 90",
        "description": "This is the description for task 90.",
        "completedAt": "2024-09-25T14:09:32Z",
        "createdAt": "2024-09-08T14:09:32Z",
        "updatedAt": "2024-10-05T14:09:32Z"
    },
    {
        "id": 91,
        "title": "Task 91",
        "description": "This is the description for task 91.",
        "completedAt": null,
        "createdAt": "2024-09-03T14:09:32Z",
        "updatedAt": null
    },
    {
        "id": 92,
        "title": "Task 92",
        "description": "This is the description for task 92.",
        "completedAt": null,
        "createdAt": "2024-08-11T14:09:32Z",
        "updatedAt": null
    },
    {
        "id": 93,
        "title": "Task 93",
        "description": "This is the description for task 93.",
        "completedAt": "2024-10-10T14:09:32Z",
        "createdAt": "2024-09-20T14:09:32Z",
        "updatedAt": "2024-10-14T14:09:32Z"
    },
    {
        "id": 94,
        "title": "Task 94",
        "description": "This is the description for task 94.",
        "completedAt": "2024-11-11T14:09:32Z",
        "createdAt": "2024-10-31T14:09:32Z",
        "updatedAt": "2024-11-13T14:09:32Z"
    },
    {
        "id": 95,
        "title": "Task 95",
        "description": "This is the description for task 95.",
        "completedAt": null,
        "createdAt": "2024-10-01T14:09:32Z",
        "updatedAt": null
    },
    {
        "id": 96,
        "title": "Task 96",
        "description": "This is the description for task 96.",
        "completedAt": null,
        "createdAt": "2024-11-02T14:09:32Z",
        "updatedAt": null
    },
    {
        "id": 97,
        "title": "Task 97",
        "description": "This is the description for task 97.",
        "completedAt": null,
        "createdAt": "2024-11-07T14:09:32Z",
        "updatedAt": null
    },
    {
        "id": 98,
        "title": "Task 98",
        "description": "This is the description for task 98.",
        "completedAt": null,
        "createdAt": "2024-10-13T14:09:32Z",
        "updatedAt": null
    },
    {
        "id": 99,
        "title": "Task 99",
        "description": "This is the description for task 99.",
        "completedAt": null,
        "createdAt": "2024-11-08T14:09:32Z",
        "updatedAt": null
    },
    {
        "id": 100,
        "title": "Task 100",
        "description": "This is the description for task 100.",
        "completedAt": "2024-08-22T14:09:32Z",
        "createdAt": "2024-08-04T14:09:32Z",
        "updatedAt": "2024-08-23T14:09:32Z"
    }
]